image_serve_api/__init__.py
image_serve_api-1.0.2.dist-info/METADATA
image_serve_api-1.0.2.dist-info/WHEEL
image_serve_api-1.0.2.dist-info/top_level.txt
image_serve_api-1.0.2.dist-info/RECORD
