Metadata-Version: 2.1
Name: image-serve-api
Version: 1.0.2
Summary: A Python package for effortless image uploads and management via the ImageServe API, ensuring seamless integration for your applications.
Author: IP Softech - Pratham Pansuriya
Author-email: ipsoftechsolutions@gmail.com
Classifier: Programming Language :: Python
Classifier: License :: OSI Approved :: MIT License
Requires-Dist: requests
